leveldb_export/__init__.py
leveldb_export/export.py
leveldb_export/records.py
leveldb_export/utils.py
leveldb_export-0.1.1.dist-info/LICENSE.md
leveldb_export-0.1.1.dist-info/WHEEL
leveldb_export-0.1.1.dist-info/METADATA
leveldb_export-0.1.1.dist-info/RECORD
